EasyEmbed/__init__.py
EasyEmbed/command_server.py
EasyEmbed/http_command_server.py
EasyEmbed/server.py
PyEasyEmbed-0.2.1.dist-info/LICENSE
PyEasyEmbed-0.2.1.dist-info/METADATA
PyEasyEmbed-0.2.1.dist-info/WHEEL
PyEasyEmbed-0.2.1.dist-info/top_level.txt
PyEasyEmbed-0.2.1.dist-info/RECORD
