Metadata-Version: 2.1
Name: PyEasyEmbed
Version: 0.2.1
Summary: Library to make integration of Python in other applications more easy
Home-page: https://github.com/swip3798/PyEasyEmbed
Author: Christian Schweigel
Author-email: 
License: UNKNOWN
Platform: UNKNOWN
Classifier: Programming Language :: Python :: 3
Classifier: Programming Language :: Python :: 3 :: Only
Classifier: License :: OSI Approved :: MIT License
Classifier: Operating System :: OS Independent
Classifier: Development Status :: 3 - Alpha
Requires-Dist: bottle (==0.12.9)
